[{"runs":"30","balls":"32","fours":"2","sixes":"0","StrikeRate":"93.75","date":"Oct 22 2020","venue":"Dubai","result":"Sunrisers won by 8 wickets (with 11 balls remaining)","OpponentName":"Sunrisers Hyderabad"},{"runs":"50","balls":"26","fours":"6","sixes":"3","StrikeRate":"192.31","date":"Oct 30 2020","venue":"Abu Dhabi","result":"Royals won by 7 wickets (with 15 balls remaining)","OpponentName":"Punjab Kings"},{"runs":"107","balls":"60","fours":"14","sixes":"3","StrikeRate":"178.33","date":"Oct 25 2020","venue":"Abu Dhabi","result":"Royals won by 8 wickets (with 10 balls remaining)","OpponentName":"Mumbai Indians"},{"runs":"19","balls":"11","fours":"3","sixes":"0","StrikeRate":"172.73","date":"Oct 19 2020","venue":"Abu Dhabi","result":"Royals won by 7 wickets (with 15 balls remaining)","OpponentName":"Chennai Super Kings"},{"runs":"15","balls":"19","fours":"2","sixes":"0","StrikeRate":"78.95","date":"Oct 17 2020","venue":"Dubai","result":"RCB won by 7 wickets (with 2 balls remaining)","OpponentName":"Royal Challengers Bangalore"},{"runs":"5","balls":"6","fours":"1","sixes":"0","StrikeRate":"83.33","date":"Oct 11 2020","venue":"Dubai","result":"Royals won by 5 wickets (with 1 ball remaining)","OpponentName":"Sunrisers Hyderabad"},{"runs":"18","balls":"11","fours":"2","sixes":"1","StrikeRate":"163.64","date":"Nov 1 2020","venue":"Dubai","result":"KKR won by 60 runs","OpponentName":"Kolkata Knight Riders"},{"runs":"41","balls":"35","fours":"6","sixes":"0","StrikeRate":"117.14","date":"Oct 14 2020","venue":"Dubai","result":"Capitals won by 13 runs","OpponentName":"Delhi Capitals"}]